PriceComp/PriceComp.py
PriceComp/__init__.py
PriceComp-0.1.6.dist-info/LICENSE.txt
PriceComp-0.1.6.dist-info/METADATA
PriceComp-0.1.6.dist-info/WHEEL
PriceComp-0.1.6.dist-info/top_level.txt
PriceComp-0.1.6.dist-info/RECORD
