Metadata-Version: 2.1
Name: PriceComp
Version: 0.1.6
Summary: Comparador de preços
Author: Ueslei Ferreira
Author-email: <ueslei392@gmail.com>
Keywords: python,first package
Classifier: License :: OSI Approved :: MIT License
Classifier: Programming Language :: Python :: 3
Classifier: Operating System :: OS Independent
License-File: LICENSE.txt
Requires-Dist: bs4
Requires-Dist: selenium
Requires-Dist: matplotlib
